skyapi/__init__.py
skyapi/api_client.py
skyapi/configuration.py
skyapi/exceptions.py
skyapi/rest.py
skyapi/api/__init__.py
skyapi/api/default_api.py
skyapi/models/__init__.py
skyapi/models/address.py
skyapi/models/api_v1_pending_txs_transaction.py
skyapi/models/api_v1_pending_txs_transaction_outputs.py
skyapi/models/block_schema.py
skyapi/models/block_schema_body.py
skyapi/models/block_verbose_schema.py
skyapi/models/block_verbose_schema_body.py
skyapi/models/block_verbose_schema_header.py
skyapi/models/inline_response200.py
skyapi/models/inline_response2001.py
skyapi/models/inline_response20010.py
skyapi/models/inline_response2002.py
skyapi/models/inline_response2003.py
skyapi/models/inline_response2004.py
skyapi/models/inline_response2005.py
skyapi/models/inline_response2006.py
skyapi/models/inline_response2007.py
skyapi/models/inline_response2008.py
skyapi/models/inline_response2008_data.py
skyapi/models/inline_response2009.py
skyapi/models/inline_response_default.py
skyapi/models/network_connection_schema.py
skyapi/models/network_connection_schema_unconfirmed_verify_transaction.py
skyapi/models/transaction.py
skyapi/models/transaction_encoded.py
skyapi/models/transaction_encoded_s.py
skyapi/models/transaction_status.py
skyapi/models/transaction_txn.py
skyapi/models/transaction_v2_params_address.py
skyapi/models/transaction_v2_params_address_hours_selection.py
skyapi/models/transaction_v2_params_unspent.py
skyapi/models/transaction_v2_params_unspent_hours_selection.py
skyapi/models/transaction_v2_params_unspent_to.py
skyapi/models/transaction_verbose.py
skyapi/models/transaction_verbose_txn.py
skyapi/models/transaction_verbose_txn_inputs.py
skyapi/models/transaction_verify_request.py
skyapi/models/wallet_transaction_request.py
skyapi/models/wallet_transaction_request_hours_selection.py
skyapi/models/wallet_transaction_request_wallet.py
skyapi/models/wallet_transaction_sign_request.py
skyapi-0.26.0.dist-info/METADATA
skyapi-0.26.0.dist-info/RECORD
skyapi-0.26.0.dist-info/WHEEL
skyapi-0.26.0.dist-info/top_level.txt
test/__init__.py
