Metadata-Version: 2.1
Name: skyapi
Version: 0.26.0
Summary: Skycoin REST API.
Home-page: UNKNOWN
Author-email: contact@skycoin.net
License: UNKNOWN
Keywords: skycoin crypto coin currency blockchain REST API
Platform: UNKNOWN
Requires-Dist: urllib3 (>=1.15)
Requires-Dist: six (>=1.10)
Requires-Dist: certifi
Requires-Dist: python-dateutil
